README.md
setup.cfg
setup.py
astpath/__init__.py
astpath/asts.py
astpath/cli.py
astpath/search.py
astpath.egg-info/PKG-INFO
astpath.egg-info/SOURCES.txt
astpath.egg-info/dependency_links.txt
astpath.egg-info/entry_points.txt
astpath.egg-info/requires.txt
astpath.egg-info/top_level.txt